{"trial_id": "21", "hyperparameters": {"space": [{"class_name": "Choice", "config": {"name": "num_layers", "default": 2, "conditions": [], "values": [2, 3, 4], "ordered": true}}, {"class_name": "Choice", "config": {"name": "lstm_units_0", "default": 64, "conditions": [], "values": [64, 128, 256], "ordered": true}}, {"class_name": "Choice", "config": {"name": "activation", "default": "tanh", "conditions": [], "values": ["tanh", "sigmoid"], "ordered": false}}, {"class_name": "Choice", "config": {"name": "dropout_0", "default": 0.1, "conditions": [], "values": [0.1, 0.2], "ordered": true}}, {"class_name": "Choice", "config": {"name": "lstm_units_1", "default": 64, "conditions": [], "values": [64], "ordered": true}}, {"class_name": "Choice", "config": {"name": "dropout_1", "default": 0.1, "conditions": [], "values": [0.1, 0.2], "ordered": true}}, {"class_name": "Choice", "config": {"name": "lstm_units_2", "default": 64, "conditions": [], "values": [64], "ordered": true}}, {"class_name": "Choice", "config": {"name": "dropout_2", "default": 0.1, "conditions": [], "values": [0.1, 0.2], "ordered": true}}, {"class_name": "Choice", "config": {"name": "lstm_units_3", "default": 64, "conditions": [], "values": [64], "ordered": true}}, {"class_name": "Choice", "config": {"name": "dropout_3", "default": 0.1, "conditions": [], "values": [0.1, 0.2], "ordered": true}}], "values": {"num_layers": 2, "lstm_units_0": 64, "activation": "sigmoid", "dropout_0": 0.1, "lstm_units_1": 64, "dropout_1": 0.2, "lstm_units_2": 64, "dropout_2": 0.2, "lstm_units_3": 64, "dropout_3": 0.1}}, "metrics": {"metrics": {"loss": {"direction": "min", "observations": [{"value": [0.4752553105354309], "step": 6}]}, "mean_absolute_percentage_error": {"direction": "min", "observations": [{"value": [483.4092712402344], "step": 6}]}, "root_mean_squared_error": {"direction": "min", "observations": [{"value": [0.6786364316940308], "step": 6}]}, "val_loss": {"direction": "min", "observations": [{"value": [0.27398717403411865], "step": 6}]}, "val_mean_absolute_percentage_error": {"direction": "min", "observations": [{"value": [590.9553833007812], "step": 6}]}, "val_root_mean_squared_error": {"direction": "min", "observations": [{"value": [0.5092095732688904], "step": 6}]}}}, "score": 0.27398717403411865, "best_step": 6, "status": "COMPLETED", "message": null}